buildbot_badges/VERSION
buildbot_badges/__init__.py
buildbot_badges/static/.placeholder
buildbot_badges/templates/badgeio.svg.j2
buildbot_badges/templates/flat-square.svg.j2
buildbot_badges/templates/flat.svg.j2
buildbot_badges/templates/plastic.svg.j2
buildbot_badges-4.3.0.dist-info/METADATA
buildbot_badges-4.3.0.dist-info/WHEEL
buildbot_badges-4.3.0.dist-info/entry_points.txt
buildbot_badges-4.3.0.dist-info/top_level.txt
buildbot_badges-4.3.0.dist-info/RECORD
