Metadata-Version: 2.1
Name: buildbot-badges
Version: 4.3.0
Summary: Buildbot badges
Home-page: http://buildbot.net/
Author: Buildbot Team Members
Author-email: users@buildbot.net
Classifier: License :: OSI Approved :: GNU General Public License v2 (GPLv2)
Requires-Dist: klein
Requires-Dist: CairoSVG
Requires-Dist: cairocffi
Requires-Dist: Jinja2
